pbhstat
