Metadata-Version: 2.1
Name: pbhstat
Version: 0.0.2
Summary: A Python code for calculating the primordial black hole mass function and abundance.
Home-page: https://github.com/pipcole/pbhstat
Download-URL: https://github.com/pipcole/pbhstat/archive/refs/tags/v.0.0.2.tar.gz
Author: Philippa Cole and Jacopo Fumagalli
Author-email: philippa.cole@unimib.it
License: MIT
Keywords: PBH,abundance,mass function
Classifier: Development Status :: 4 - Beta
Classifier: Intended Audience :: Developers
Classifier: Topic :: Software Development :: Build Tools
Classifier: License :: OSI Approved :: MIT License
Classifier: Programming Language :: Python :: 3.9
Classifier: Programming Language :: Python :: 3.11
Classifier: Programming Language :: Python :: 3.12
License-File: LICENSE.txt
